{
    "setspec": {
        "clusters": [
            {
                "stims": [
                    {
                        "response": {
                            "correctResponse": "tone 1"
                        },
                        "display": {
                            "audioSrc": "sounds/toneresource/1.4ma/T1_400ms__vowel.wav"
                        }
                    }
                ]
            },
            {
                "stims": [
                    {
                        "response": {
                            "correctResponse": "tone 1"
                        },
                        "display": {
                            "audioSrc": "sounds/toneresource/1.4ma/T1_400ms__vowel_changeGender.wav"
                        }
                    }
                ]
            },
            {
                "stims": [
                    {
                        "response": {
                            "correctResponse": "tone 1"
                        },
                        "display": {
                            "audioSrc": "sounds/toneresource/1.0ma/T1_400ms__vowel.wav"
                        }
                    }
                ]
            },
            {
                "stims": [
                    {
                        "response": {
                            "correctResponse": "tone 1"
                        },
                        "display": {
                            "audioSrc": "sounds/toneresource/1.0ma/T1_400ms__vowel_changeGender.wav"
                        }
                    }
                ]
            },
            {
                "stims": [
                    {
                        "response": {
                            "correctResponse": "tone 1"
                        },
                        "display": {
                            "audioSrc": "sounds/toneresource/1.8ma/T1_400ms__vowel.wav"
                        }
                    }
                ]
            },
            {
                "stims": [
                    {
                        "response": {
                            "correctResponse": "tone 1"
                        },
                        "display": {
                            "audioSrc": "sounds/toneresource/1.8ma/T1_400ms__vowel_changeGender.wav"
                        }
                    }
                ]
            },
            {
                "stims": [
                    {
                        "response": {
                            "correctResponse": "tone 1"
                        },
                        "display": {
                            "audioSrc": "sounds/toneresource/1.4ma/T1_800ms__vowel.wav"
                        }
                    }
                ]
            },
            {
                "stims": [
                    {
                        "response": {
                            "correctResponse": "tone 1"
                        },
                        "display": {
                            "audioSrc": "sounds/toneresource/1.4ma/T1_800ms__vowel_changeGender.wav"
                        }
                    }
                ]
            },
            {
                "stims": [
                    {
                        "response": {
                            "correctResponse": "tone 1"
                        },
                        "display": {
                            "audioSrc": "sounds/toneresource/1.0ma/T1_800ms__vowel.wav"
                        }
                    }
                ]
            },
            {
                "stims": [
                    {
                        "response": {
                            "correctResponse": "tone 1"
                        },
                        "display": {
                            "audioSrc": "sounds/toneresource/1.0ma/T1_800ms__vowel_changeGender.wav"
                        }
                    }
                ]
            },
            {
                "stims": [
                    {
                        "response": {
                            "correctResponse": "tone 1"
                        },
                        "display": {
                            "audioSrc": "sounds/toneresource/1.8ma/T1_800ms__vowel.wav"
                        }
                    }
                ]
            },
            {
                "stims": [
                    {
                        "response": {
                            "correctResponse": "tone 1"
                        },
                        "display": {
                            "audioSrc": "sounds/toneresource/1.8ma/T1_800ms__vowel_changeGender.wav"
                        }
                    }
                ]
            },
            {
                "stims": [
                    {
                        "response": {
                            "correctResponse": "tone 1"
                        },
                        "display": {
                            "audioSrc": "sounds/toneresource/1.4ma/T1_1200ms__vowel.wav"
                        }
                    }
                ]
            },
            {
                "stims": [
                    {
                        "response": {
                            "correctResponse": "tone 1"
                        },
                        "display": {
                            "audioSrc": "sounds/toneresource/1.4ma/T1_1200ms__vowel_changeGender.wav"
                        }
                    }
                ]
            },
            {
                "stims": [
                    {
                        "response": {
                            "correctResponse": "tone 1"
                        },
                        "display": {
                            "audioSrc": "sounds/toneresource/1.0ma/T1_1200ms__vowel.wav"
                        }
                    }
                ]
            },
            {
                "stims": [
                    {
                        "response": {
                            "correctResponse": "tone 1"
                        },
                        "display": {
                            "audioSrc": "sounds/toneresource/1.0ma/T1_1200ms__vowel_changeGender.wav"
                        }
                    }
                ]
            },
            {
                "stims": [
                    {
                        "response": {
                            "correctResponse": "tone 1"
                        },
                        "display": {
                            "audioSrc": "sounds/toneresource/1.8ma/T1_1200ms__vowel.wav"
                        }
                    }
                ]
            },
            {
                "stims": [
                    {
                        "response": {
                            "correctResponse": "tone 1"
                        },
                        "display": {
                            "audioSrc": "sounds/toneresource/1.8ma/T1_1200ms__vowel_changeGender.wav"
                        }
                    }
                ]
            },
            {
                "stims": [
                    {
                        "response": {
                            "correctResponse": "tone 1"
                        },
                        "display": {
                            "audioSrc": "sounds/toneresource/1.4ya/T1_400ms__vowel.wav"
                        }
                    }
                ]
            },
            {
                "stims": [
                    {
                        "response": {
                            "correctResponse": "tone 1"
                        },
                        "display": {
                            "audioSrc": "sounds/toneresource/1.4ya/T1_400ms__vowel_changeGender.wav"
                        }
                    }
                ]
            },
            {
                "stims": [
                    {
                        "response": {
                            "correctResponse": "tone 1"
                        },
                        "display": {
                            "audioSrc": "sounds/toneresource/1.0ya/T1_400ms__vowel.wav"
                        }
                    }
                ]
            },
            {
                "stims": [
                    {
                        "response": {
                            "correctResponse": "tone 1"
                        },
                        "display": {
                            "audioSrc": "sounds/toneresource/1.0ya/T1_400ms__vowel_changeGender.wav"
                        }
                    }
                ]
            },
            {
                "stims": [
                    {
                        "response": {
                            "correctResponse": "tone 1"
                        },
                        "display": {
                            "audioSrc": "sounds/toneresource/1.8ya/T1_400ms__vowel.wav"
                        }
                    }
                ]
            },
            {
                "stims": [
                    {
                        "response": {
                            "correctResponse": "tone 1"
                        },
                        "display": {
                            "audioSrc": "sounds/toneresource/1.8ya/T1_400ms__vowel_changeGender.wav"
                        }
                    }
                ]
            },
            {
                "stims": [
                    {
                        "response": {
                            "correctResponse": "tone 1"
                        },
                        "display": {
                            "audioSrc": "sounds/toneresource/1.4ya/T1_800ms__vowel.wav"
                        }
                    }
                ]
            },
            {
                "stims": [
                    {
                        "response": {
                            "correctResponse": "tone 1"
                        },
                        "display": {
                            "audioSrc": "sounds/toneresource/1.4ya/T1_800ms__vowel_changeGender.wav"
                        }
                    }
                ]
            },
            {
                "stims": [
                    {
                        "response": {
                            "correctResponse": "tone 1"
                        },
                        "display": {
                            "audioSrc": "sounds/toneresource/1.0ya/T1_800ms__vowel.wav"
                        }
                    }
                ]
            },
            {
                "stims": [
                    {
                        "response": {
                            "correctResponse": "tone 1"
                        },
                        "display": {
                            "audioSrc": "sounds/toneresource/1.0ya/T1_800ms__vowel_changeGender.wav"
                        }
                    }
                ]
            },
            {
                "stims": [
                    {
                        "response": {
                            "correctResponse": "tone 1"
                        },
                        "display": {
                            "audioSrc": "sounds/toneresource/1.8ya/T1_800ms__vowel.wav"
                        }
                    }
                ]
            },
            {
                "stims": [
                    {
                        "response": {
                            "correctResponse": "tone 1"
                        },
                        "display": {
                            "audioSrc": "sounds/toneresource/1.8ya/T1_800ms__vowel_changeGender.wav"
                        }
                    }
                ]
            },
            {
                "stims": [
                    {
                        "response": {
                            "correctResponse": "tone 1"
                        },
                        "display": {
                            "audioSrc": "sounds/toneresource/1.4ya/T1_1200ms__vowel.wav"
                        }
                    }
                ]
            },
            {
                "stims": [
                    {
                        "response": {
                            "correctResponse": "tone 1"
                        },
                        "display": {
                            "audioSrc": "sounds/toneresource/1.4ya/T1_1200ms__vowel_changeGender.wav"
                        }
                    }
                ]
            },
            {
                "stims": [
                    {
                        "response": {
                            "correctResponse": "tone 1"
                        },
                        "display": {
                            "audioSrc": "sounds/toneresource/1.0ya/T1_1200ms__vowel.wav"
                        }
                    }
                ]
            },
            {
                "stims": [
                    {
                        "response": {
                            "correctResponse": "tone 1"
                        },
                        "display": {
                            "audioSrc": "sounds/toneresource/1.0ya/T1_1200ms__vowel_changeGender.wav"
                        }
                    }
                ]
            },
            {
                "stims": [
                    {
                        "response": {
                            "correctResponse": "tone 1"
                        },
                        "display": {
                            "audioSrc": "sounds/toneresource/1.8ya/T1_1200ms__vowel.wav"
                        }
                    }
                ]
            },
            {
                "stims": [
                    {
                        "response": {
                            "correctResponse": "tone 1"
                        },
                        "display": {
                            "audioSrc": "sounds/toneresource/1.8ya/T1_1200ms__vowel_changeGender.wav"
                        }
                    }
                ]
            },
            {
                "stims": [
                    {
                        "response": {
                            "correctResponse": "tone 1"
                        },
                        "display": {
                            "audioSrc": "sounds/toneresource/1.4mo/T1_400ms__vowel.wav"
                        }
                    }
                ]
            },
            {
                "stims": [
                    {
                        "response": {
                            "correctResponse": "tone 1"
                        },
                        "display": {
                            "audioSrc": "sounds/toneresource/1.4mo/T1_400ms__vowel_changeGender.wav"
                        }
                    }
                ]
            },
            {
                "stims": [
                    {
                        "response": {
                            "correctResponse": "tone 1"
                        },
                        "display": {
                            "audioSrc": "sounds/toneresource/1.0mo/T1_400ms__vowel.wav"
                        }
                    }
                ]
            },
            {
                "stims": [
                    {
                        "response": {
                            "correctResponse": "tone 1"
                        },
                        "display": {
                            "audioSrc": "sounds/toneresource/1.0mo/T1_400ms__vowel_changeGender.wav"
                        }
                    }
                ]
            },
            {
                "stims": [
                    {
                        "response": {
                            "correctResponse": "tone 1"
                        },
                        "display": {
                            "audioSrc": "sounds/toneresource/1.8mo/T1_400ms__vowel.wav"
                        }
                    }
                ]
            },
            {
                "stims": [
                    {
                        "response": {
                            "correctResponse": "tone 1"
                        },
                        "display": {
                            "audioSrc": "sounds/toneresource/1.8mo/T1_400ms__vowel_changeGender.wav"
                        }
                    }
                ]
            },
            {
                "stims": [
                    {
                        "response": {
                            "correctResponse": "tone 1"
                        },
                        "display": {
                            "audioSrc": "sounds/toneresource/1.4mo/T1_800ms__vowel.wav"
                        }
                    }
                ]
            },
            {
                "stims": [
                    {
                        "response": {
                            "correctResponse": "tone 1"
                        },
                        "display": {
                            "audioSrc": "sounds/toneresource/1.4mo/T1_800ms__vowel_changeGender.wav"
                        }
                    }
                ]
            },
            {
                "stims": [
                    {
                        "response": {
                            "correctResponse": "tone 1"
                        },
                        "display": {
                            "audioSrc": "sounds/toneresource/1.0mo/T1_800ms__vowel.wav"
                        }
                    }
                ]
            },
            {
                "stims": [
                    {
                        "response": {
                            "correctResponse": "tone 1"
                        },
                        "display": {
                            "audioSrc": "sounds/toneresource/1.0mo/T1_800ms__vowel_changeGender.wav"
                        }
                    }
                ]
            },
            {
                "stims": [
                    {
                        "response": {
                            "correctResponse": "tone 1"
                        },
                        "display": {
                            "audioSrc": "sounds/toneresource/1.8mo/T1_800ms__vowel.wav"
                        }
                    }
                ]
            },
            {
                "stims": [
                    {
                        "response": {
                            "correctResponse": "tone 1"
                        },
                        "display": {
                            "audioSrc": "sounds/toneresource/1.8mo/T1_800ms__vowel_changeGender.wav"
                        }
                    }
                ]
            },
            {
                "stims": [
                    {
                        "response": {
                            "correctResponse": "tone 1"
                        },
                        "display": {
                            "audioSrc": "sounds/toneresource/1.4mo/T1_1200ms__vowel.wav"
                        }
                    }
                ]
            },
            {
                "stims": [
                    {
                        "response": {
                            "correctResponse": "tone 1"
                        },
                        "display": {
                            "audioSrc": "sounds/toneresource/1.4mo/T1_1200ms__vowel_changeGender.wav"
                        }
                    }
                ]
            },
            {
                "stims": [
                    {
                        "response": {
                            "correctResponse": "tone 1"
                        },
                        "display": {
                            "audioSrc": "sounds/toneresource/1.0mo/T1_1200ms__vowel.wav"
                        }
                    }
                ]
            },
            {
                "stims": [
                    {
                        "response": {
                            "correctResponse": "tone 1"
                        },
                        "display": {
                            "audioSrc": "sounds/toneresource/1.0mo/T1_1200ms__vowel_changeGender.wav"
                        }
                    }
                ]
            },
            {
                "stims": [
                    {
                        "response": {
                            "correctResponse": "tone 1"
                        },
                        "display": {
                            "audioSrc": "sounds/toneresource/1.8mo/T1_1200ms__vowel.wav"
                        }
                    }
                ]
            },
            {
                "stims": [
                    {
                        "response": {
                            "correctResponse": "tone 1"
                        },
                        "display": {
                            "audioSrc": "sounds/toneresource/1.8mo/T1_1200ms__vowel_changeGender.wav"
                        }
                    }
                ]
            },
            {
                "stims": [
                    {
                        "response": {
                            "correctResponse": "tone 2"
                        },
                        "display": {
                            "audioSrc": "sounds/toneresource/1.4ma/T2_400ms__vowel.wav"
                        }
                    }
                ]
            },
            {
                "stims": [
                    {
                        "response": {
                            "correctResponse": "tone 2"
                        },
                        "display": {
                            "audioSrc": "sounds/toneresource/1.4ma/T2_400ms__vowel_changeGender.wav"
                        }
                    }
                ]
            },
            {
                "stims": [
                    {
                        "response": {
                            "correctResponse": "tone 2"
                        },
                        "display": {
                            "audioSrc": "sounds/toneresource/1.0ma/T2_400ms__vowel.wav"
                        }
                    }
                ]
            },
            {
                "stims": [
                    {
                        "response": {
                            "correctResponse": "tone 2"
                        },
                        "display": {
                            "audioSrc": "sounds/toneresource/1.0ma/T2_400ms__vowel_changeGender.wav"
                        }
                    }
                ]
            },
            {
                "stims": [
                    {
                        "response": {
                            "correctResponse": "tone 2"
                        },
                        "display": {
                            "audioSrc": "sounds/toneresource/1.8ma/T2_400ms__vowel.wav"
                        }
                    }
                ]
            },
            {
                "stims": [
                    {
                        "response": {
                            "correctResponse": "tone 2"
                        },
                        "display": {
                            "audioSrc": "sounds/toneresource/1.8ma/T2_400ms__vowel_changeGender.wav"
                        }
                    }
                ]
            },
            {
                "stims": [
                    {
                        "response": {
                            "correctResponse": "tone 2"
                        },
                        "display": {
                            "audioSrc": "sounds/toneresource/1.4ma/T2_800ms__vowel.wav"
                        }
                    }
                ]
            },
            {
                "stims": [
                    {
                        "response": {
                            "correctResponse": "tone 2"
                        },
                        "display": {
                            "audioSrc": "sounds/toneresource/1.4ma/T2_800ms__vowel_changeGender.wav"
                        }
                    }
                ]
            },
            {
                "stims": [
                    {
                        "response": {
                            "correctResponse": "tone 2"
                        },
                        "display": {
                            "audioSrc": "sounds/toneresource/1.0ma/T2_800ms__vowel.wav"
                        }
                    }
                ]
            },
            {
                "stims": [
                    {
                        "response": {
                            "correctResponse": "tone 2"
                        },
                        "display": {
                            "audioSrc": "sounds/toneresource/1.0ma/T2_800ms__vowel_changeGender.wav"
                        }
                    }
                ]
            },
            {
                "stims": [
                    {
                        "response": {
                            "correctResponse": "tone 2"
                        },
                        "display": {
                            "audioSrc": "sounds/toneresource/1.8ma/T2_800ms__vowel.wav"
                        }
                    }
                ]
            },
            {
                "stims": [
                    {
                        "response": {
                            "correctResponse": "tone 2"
                        },
                        "display": {
                            "audioSrc": "sounds/toneresource/1.8ma/T2_800ms__vowel_changeGender.wav"
                        }
                    }
                ]
            },
            {
                "stims": [
                    {
                        "response": {
                            "correctResponse": "tone 2"
                        },
                        "display": {
                            "audioSrc": "sounds/toneresource/1.4ma/T2_1200ms__vowel.wav"
                        }
                    }
                ]
            },
            {
                "stims": [
                    {
                        "response": {
                            "correctResponse": "tone 2"
                        },
                        "display": {
                            "audioSrc": "sounds/toneresource/1.4ma/T2_1200ms__vowel_changeGender.wav"
                        }
                    }
                ]
            },
            {
                "stims": [
                    {
                        "response": {
                            "correctResponse": "tone 2"
                        },
                        "display": {
                            "audioSrc": "sounds/toneresource/1.0ma/T2_1200ms__vowel.wav"
                        }
                    }
                ]
            },
            {
                "stims": [
                    {
                        "response": {
                            "correctResponse": "tone 2"
                        },
                        "display": {
                            "audioSrc": "sounds/toneresource/1.0ma/T2_1200ms__vowel_changeGender.wav"
                        }
                    }
                ]
            },
            {
                "stims": [
                    {
                        "response": {
                            "correctResponse": "tone 2"
                        },
                        "display": {
                            "audioSrc": "sounds/toneresource/1.8ma/T2_1200ms__vowel.wav"
                        }
                    }
                ]
            },
            {
                "stims": [
                    {
                        "response": {
                            "correctResponse": "tone 2"
                        },
                        "display": {
                            "audioSrc": "sounds/toneresource/1.8ma/T2_1200ms__vowel_changeGender.wav"
                        }
                    }
                ]
            },
            {
                "stims": [
                    {
                        "response": {
                            "correctResponse": "tone 2"
                        },
                        "display": {
                            "audioSrc": "sounds/toneresource/1.4ya/T2_400ms__vowel.wav"
                        }
                    }
                ]
            },
            {
                "stims": [
                    {
                        "response": {
                            "correctResponse": "tone 2"
                        },
                        "display": {
                            "audioSrc": "sounds/toneresource/1.4ya/T2_400ms__vowel_changeGender.wav"
                        }
                    }
                ]
            },
            {
                "stims": [
                    {
                        "response": {
                            "correctResponse": "tone 2"
                        },
                        "display": {
                            "audioSrc": "sounds/toneresource/1.0ya/T2_400ms__vowel.wav"
                        }
                    }
                ]
            },
            {
                "stims": [
                    {
                        "response": {
                            "correctResponse": "tone 2"
                        },
                        "display": {
                            "audioSrc": "sounds/toneresource/1.0ya/T2_400ms__vowel_changeGender.wav"
                        }
                    }
                ]
            },
            {
                "stims": [
                    {
                        "response": {
                            "correctResponse": "tone 2"
                        },
                        "display": {
                            "audioSrc": "sounds/toneresource/1.8ya/T2_400ms__vowel.wav"
                        }
                    }
                ]
            },
            {
                "stims": [
                    {
                        "response": {
                            "correctResponse": "tone 2"
                        },
                        "display": {
                            "audioSrc": "sounds/toneresource/1.8ya/T2_400ms__vowel_changeGender.wav"
                        }
                    }
                ]
            },
            {
                "stims": [
                    {
                        "response": {
                            "correctResponse": "tone 2"
                        },
                        "display": {
                            "audioSrc": "sounds/toneresource/1.4ya/T2_800ms__vowel.wav"
                        }
                    }
                ]
            },
            {
                "stims": [
                    {
                        "response": {
                            "correctResponse": "tone 2"
                        },
                        "display": {
                            "audioSrc": "sounds/toneresource/1.4ya/T2_800ms__vowel_changeGender.wav"
                        }
                    }
                ]
            },
            {
                "stims": [
                    {
                        "response": {
                            "correctResponse": "tone 2"
                        },
                        "display": {
                            "audioSrc": "sounds/toneresource/1.0ya/T2_800ms__vowel.wav"
                        }
                    }
                ]
            },
            {
                "stims": [
                    {
                        "response": {
                            "correctResponse": "tone 2"
                        },
                        "display": {
                            "audioSrc": "sounds/toneresource/1.0ya/T2_800ms__vowel_changeGender.wav"
                        }
                    }
                ]
            },
            {
                "stims": [
                    {
                        "response": {
                            "correctResponse": "tone 2"
                        },
                        "display": {
                            "audioSrc": "sounds/toneresource/1.8ya/T2_800ms__vowel.wav"
                        }
                    }
                ]
            },
            {
                "stims": [
                    {
                        "response": {
                            "correctResponse": "tone 2"
                        },
                        "display": {
                            "audioSrc": "sounds/toneresource/1.8ya/T2_800ms__vowel_changeGender.wav"
                        }
                    }
                ]
            },
            {
                "stims": [
                    {
                        "response": {
                            "correctResponse": "tone 2"
                        },
                        "display": {
                            "audioSrc": "sounds/toneresource/1.4ya/T2_1200ms__vowel.wav"
                        }
                    }
                ]
            },
            {
                "stims": [
                    {
                        "response": {
                            "correctResponse": "tone 2"
                        },
                        "display": {
                            "audioSrc": "sounds/toneresource/1.4ya/T2_1200ms__vowel_changeGender.wav"
                        }
                    }
                ]
            },
            {
                "stims": [
                    {
                        "response": {
                            "correctResponse": "tone 2"
                        },
                        "display": {
                            "audioSrc": "sounds/toneresource/1.0ya/T2_1200ms__vowel.wav"
                        }
                    }
                ]
            },
            {
                "stims": [
                    {
                        "response": {
                            "correctResponse": "tone 2"
                        },
                        "display": {
                            "audioSrc": "sounds/toneresource/1.0ya/T2_1200ms__vowel_changeGender.wav"
                        }
                    }
                ]
            },
            {
                "stims": [
                    {
                        "response": {
                            "correctResponse": "tone 2"
                        },
                        "display": {
                            "audioSrc": "sounds/toneresource/1.8ya/T2_1200ms__vowel.wav"
                        }
                    }
                ]
            },
            {
                "stims": [
                    {
                        "response": {
                            "correctResponse": "tone 2"
                        },
                        "display": {
                            "audioSrc": "sounds/toneresource/1.8ya/T2_1200ms__vowel_changeGender.wav"
                        }
                    }
                ]
            },
            {
                "stims": [
                    {
                        "response": {
                            "correctResponse": "tone 2"
                        },
                        "display": {
                            "audioSrc": "sounds/toneresource/1.4mo/T2_400ms__vowel.wav"
                        }
                    }
                ]
            },
            {
                "stims": [
                    {
                        "response": {
                            "correctResponse": "tone 2"
                        },
                        "display": {
                            "audioSrc": "sounds/toneresource/1.4mo/T2_400ms__vowel_changeGender.wav"
                        }
                    }
                ]
            },
            {
                "stims": [
                    {
                        "response": {
                            "correctResponse": "tone 2"
                        },
                        "display": {
                            "audioSrc": "sounds/toneresource/1.0mo/T2_400ms__vowel.wav"
                        }
                    }
                ]
            },
            {
                "stims": [
                    {
                        "response": {
                            "correctResponse": "tone 2"
                        },
                        "display": {
                            "audioSrc": "sounds/toneresource/1.0mo/T2_400ms__vowel_changeGender.wav"
                        }
                    }
                ]
            },
            {
                "stims": [
                    {
                        "response": {
                            "correctResponse": "tone 2"
                        },
                        "display": {
                            "audioSrc": "sounds/toneresource/1.8mo/T2_400ms__vowel.wav"
                        }
                    }
                ]
            },
            {
                "stims": [
                    {
                        "response": {
                            "correctResponse": "tone 2"
                        },
                        "display": {
                            "audioSrc": "sounds/toneresource/1.8mo/T2_400ms__vowel_changeGender.wav"
                        }
                    }
                ]
            },
            {
                "stims": [
                    {
                        "response": {
                            "correctResponse": "tone 2"
                        },
                        "display": {
                            "audioSrc": "sounds/toneresource/1.4mo/T2_800ms__vowel.wav"
                        }
                    }
                ]
            },
            {
                "stims": [
                    {
                        "response": {
                            "correctResponse": "tone 2"
                        },
                        "display": {
                            "audioSrc": "sounds/toneresource/1.4mo/T2_800ms__vowel_changeGender.wav"
                        }
                    }
                ]
            },
            {
                "stims": [
                    {
                        "response": {
                            "correctResponse": "tone 2"
                        },
                        "display": {
                            "audioSrc": "sounds/toneresource/1.0mo/T2_800ms__vowel.wav"
                        }
                    }
                ]
            },
            {
                "stims": [
                    {
                        "response": {
                            "correctResponse": "tone 2"
                        },
                        "display": {
                            "audioSrc": "sounds/toneresource/1.0mo/T2_800ms__vowel_changeGender.wav"
                        }
                    }
                ]
            },
            {
                "stims": [
                    {
                        "response": {
                            "correctResponse": "tone 2"
                        },
                        "display": {
                            "audioSrc": "sounds/toneresource/1.8mo/T2_800ms__vowel.wav"
                        }
                    }
                ]
            },
            {
                "stims": [
                    {
                        "response": {
                            "correctResponse": "tone 2"
                        },
                        "display": {
                            "audioSrc": "sounds/toneresource/1.8mo/T2_800ms__vowel_changeGender.wav"
                        }
                    }
                ]
            },
            {
                "stims": [
                    {
                        "response": {
                            "correctResponse": "tone 2"
                        },
                        "display": {
                            "audioSrc": "sounds/toneresource/1.4mo/T2_1200ms__vowel.wav"
                        }
                    }
                ]
            },
            {
                "stims": [
                    {
                        "response": {
                            "correctResponse": "tone 2"
                        },
                        "display": {
                            "audioSrc": "sounds/toneresource/1.4mo/T2_1200ms__vowel_changeGender.wav"
                        }
                    }
                ]
            },
            {
                "stims": [
                    {
                        "response": {
                            "correctResponse": "tone 2"
                        },
                        "display": {
                            "audioSrc": "sounds/toneresource/1.0mo/T2_1200ms__vowel.wav"
                        }
                    }
                ]
            },
            {
                "stims": [
                    {
                        "response": {
                            "correctResponse": "tone 2"
                        },
                        "display": {
                            "audioSrc": "sounds/toneresource/1.0mo/T2_1200ms__vowel_changeGender.wav"
                        }
                    }
                ]
            },
            {
                "stims": [
                    {
                        "response": {
                            "correctResponse": "tone 2"
                        },
                        "display": {
                            "audioSrc": "sounds/toneresource/1.8mo/T2_1200ms__vowel.wav"
                        }
                    }
                ]
            },
            {
                "stims": [
                    {
                        "response": {
                            "correctResponse": "tone 2"
                        },
                        "display": {
                            "audioSrc": "sounds/toneresource/1.8mo/T2_1200ms__vowel_changeGender.wav"
                        }
                    }
                ]
            },
            {
                "stims": [
                    {
                        "response": {
                            "correctResponse": "tone 3"
                        },
                        "display": {
                            "audioSrc": "sounds/toneresource/1.4ma/T3_400ms__vowel.wav"
                        }
                    }
                ]
            },
            {
                "stims": [
                    {
                        "response": {
                            "correctResponse": "tone 3"
                        },
                        "display": {
                            "audioSrc": "sounds/toneresource/1.4ma/T3_400ms__vowel_changeGender.wav"
                        }
                    }
                ]
            },
            {
                "stims": [
                    {
                        "response": {
                            "correctResponse": "tone 3"
                        },
                        "display": {
                            "audioSrc": "sounds/toneresource/1.0ma/T3_400ms__vowel.wav"
                        }
                    }
                ]
            },
            {
                "stims": [
                    {
                        "response": {
                            "correctResponse": "tone 3"
                        },
                        "display": {
                            "audioSrc": "sounds/toneresource/1.0ma/T3_400ms__vowel_changeGender.wav"
                        }
                    }
                ]
            },
            {
                "stims": [
                    {
                        "response": {
                            "correctResponse": "tone 3"
                        },
                        "display": {
                            "audioSrc": "sounds/toneresource/1.8ma/T3_400ms__vowel.wav"
                        }
                    }
                ]
            },
            {
                "stims": [
                    {
                        "response": {
                            "correctResponse": "tone 3"
                        },
                        "display": {
                            "audioSrc": "sounds/toneresource/1.8ma/T3_400ms__vowel_changeGender.wav"
                        }
                    }
                ]
            },
            {
                "stims": [
                    {
                        "response": {
                            "correctResponse": "tone 3"
                        },
                        "display": {
                            "audioSrc": "sounds/toneresource/1.4ma/T3_800ms__vowel.wav"
                        }
                    }
                ]
            },
            {
                "stims": [
                    {
                        "response": {
                            "correctResponse": "tone 3"
                        },
                        "display": {
                            "audioSrc": "sounds/toneresource/1.4ma/T3_800ms__vowel_changeGender.wav"
                        }
                    }
                ]
            },
            {
                "stims": [
                    {
                        "response": {
                            "correctResponse": "tone 3"
                        },
                        "display": {
                            "audioSrc": "sounds/toneresource/1.0ma/T3_800ms__vowel.wav"
                        }
                    }
                ]
            },
            {
                "stims": [
                    {
                        "response": {
                            "correctResponse": "tone 3"
                        },
                        "display": {
                            "audioSrc": "sounds/toneresource/1.0ma/T3_800ms__vowel_changeGender.wav"
                        }
                    }
                ]
            },
            {
                "stims": [
                    {
                        "response": {
                            "correctResponse": "tone 3"
                        },
                        "display": {
                            "audioSrc": "sounds/toneresource/1.8ma/T3_800ms__vowel.wav"
                        }
                    }
                ]
            },
            {
                "stims": [
                    {
                        "response": {
                            "correctResponse": "tone 3"
                        },
                        "display": {
                            "audioSrc": "sounds/toneresource/1.8ma/T3_800ms__vowel_changeGender.wav"
                        }
                    }
                ]
            },
            {
                "stims": [
                    {
                        "response": {
                            "correctResponse": "tone 3"
                        },
                        "display": {
                            "audioSrc": "sounds/toneresource/1.4ma/T3_1200ms__vowel.wav"
                        }
                    }
                ]
            },
            {
                "stims": [
                    {
                        "response": {
                            "correctResponse": "tone 3"
                        },
                        "display": {
                            "audioSrc": "sounds/toneresource/1.4ma/T3_1200ms__vowel_changeGender.wav"
                        }
                    }
                ]
            },
            {
                "stims": [
                    {
                        "response": {
                            "correctResponse": "tone 3"
                        },
                        "display": {
                            "audioSrc": "sounds/toneresource/1.0ma/T3_1200ms__vowel.wav"
                        }
                    }
                ]
            },
            {
                "stims": [
                    {
                        "response": {
                            "correctResponse": "tone 3"
                        },
                        "display": {
                            "audioSrc": "sounds/toneresource/1.0ma/T3_1200ms__vowel_changeGender.wav"
                        }
                    }
                ]
            },
            {
                "stims": [
                    {
                        "response": {
                            "correctResponse": "tone 3"
                        },
                        "display": {
                            "audioSrc": "sounds/toneresource/1.8ma/T3_1200ms__vowel.wav"
                        }
                    }
                ]
            },
            {
                "stims": [
                    {
                        "response": {
                            "correctResponse": "tone 3"
                        },
                        "display": {
                            "audioSrc": "sounds/toneresource/1.8ma/T3_1200ms__vowel_changeGender.wav"
                        }
                    }
                ]
            },
            {
                "stims": [
                    {
                        "response": {
                            "correctResponse": "tone 3"
                        },
                        "display": {
                            "audioSrc": "sounds/toneresource/1.4ya/T3_400ms__vowel.wav"
                        }
                    }
                ]
            },
            {
                "stims": [
                    {
                        "response": {
                            "correctResponse": "tone 3"
                        },
                        "display": {
                            "audioSrc": "sounds/toneresource/1.4ya/T3_400ms__vowel_changeGender.wav"
                        }
                    }
                ]
            },
            {
                "stims": [
                    {
                        "response": {
                            "correctResponse": "tone 3"
                        },
                        "display": {
                            "audioSrc": "sounds/toneresource/1.0ya/T3_400ms__vowel.wav"
                        }
                    }
                ]
            },
            {
                "stims": [
                    {
                        "response": {
                            "correctResponse": "tone 3"
                        },
                        "display": {
                            "audioSrc": "sounds/toneresource/1.0ya/T3_400ms__vowel_changeGender.wav"
                        }
                    }
                ]
            },
            {
                "stims": [
                    {
                        "response": {
                            "correctResponse": "tone 3"
                        },
                        "display": {
                            "audioSrc": "sounds/toneresource/1.8ya/T3_400ms__vowel.wav"
                        }
                    }
                ]
            },
            {
                "stims": [
                    {
                        "response": {
                            "correctResponse": "tone 3"
                        },
                        "display": {
                            "audioSrc": "sounds/toneresource/1.8ya/T3_400ms__vowel_changeGender.wav"
                        }
                    }
                ]
            },
            {
                "stims": [
                    {
                        "response": {
                            "correctResponse": "tone 3"
                        },
                        "display": {
                            "audioSrc": "sounds/toneresource/1.4ya/T3_800ms__vowel.wav"
                        }
                    }
                ]
            },
            {
                "stims": [
                    {
                        "response": {
                            "correctResponse": "tone 3"
                        },
                        "display": {
                            "audioSrc": "sounds/toneresource/1.4ya/T3_800ms__vowel_changeGender.wav"
                        }
                    }
                ]
            },
            {
                "stims": [
                    {
                        "response": {
                            "correctResponse": "tone 3"
                        },
                        "display": {
                            "audioSrc": "sounds/toneresource/1.0ya/T3_800ms__vowel.wav"
                        }
                    }
                ]
            },
            {
                "stims": [
                    {
                        "response": {
                            "correctResponse": "tone 3"
                        },
                        "display": {
                            "audioSrc": "sounds/toneresource/1.0ya/T3_800ms__vowel_changeGender.wav"
                        }
                    }
                ]
            },
            {
                "stims": [
                    {
                        "response": {
                            "correctResponse": "tone 3"
                        },
                        "display": {
                            "audioSrc": "sounds/toneresource/1.8ya/T3_800ms__vowel.wav"
                        }
                    }
                ]
            },
            {
                "stims": [
                    {
                        "response": {
                            "correctResponse": "tone 3"
                        },
                        "display": {
                            "audioSrc": "sounds/toneresource/1.8ya/T3_800ms__vowel_changeGender.wav"
                        }
                    }
                ]
            },
            {
                "stims": [
                    {
                        "response": {
                            "correctResponse": "tone 3"
                        },
                        "display": {
                            "audioSrc": "sounds/toneresource/1.4ya/T3_1200ms__vowel.wav"
                        }
                    }
                ]
            },
            {
                "stims": [
                    {
                        "response": {
                            "correctResponse": "tone 3"
                        },
                        "display": {
                            "audioSrc": "sounds/toneresource/1.4ya/T3_1200ms__vowel_changeGender.wav"
                        }
                    }
                ]
            },
            {
                "stims": [
                    {
                        "response": {
                            "correctResponse": "tone 3"
                        },
                        "display": {
                            "audioSrc": "sounds/toneresource/1.0ya/T3_1200ms__vowel.wav"
                        }
                    }
                ]
            },
            {
                "stims": [
                    {
                        "response": {
                            "correctResponse": "tone 3"
                        },
                        "display": {
                            "audioSrc": "sounds/toneresource/1.0ya/T3_1200ms__vowel_changeGender.wav"
                        }
                    }
                ]
            },
            {
                "stims": [
                    {
                        "response": {
                            "correctResponse": "tone 3"
                        },
                        "display": {
                            "audioSrc": "sounds/toneresource/1.8ya/T3_1200ms__vowel.wav"
                        }
                    }
                ]
            },
            {
                "stims": [
                    {
                        "response": {
                            "correctResponse": "tone 3"
                        },
                        "display": {
                            "audioSrc": "sounds/toneresource/1.8ya/T3_1200ms__vowel_changeGender.wav"
                        }
                    }
                ]
            },
            {
                "stims": [
                    {
                        "response": {
                            "correctResponse": "tone 3"
                        },
                        "display": {
                            "audioSrc": "sounds/toneresource/1.4mo/T3_400ms__vowel.wav"
                        }
                    }
                ]
            },
            {
                "stims": [
                    {
                        "response": {
                            "correctResponse": "tone 3"
                        },
                        "display": {
                            "audioSrc": "sounds/toneresource/1.4mo/T3_400ms__vowel_changeGender.wav"
                        }
                    }
                ]
            },
            {
                "stims": [
                    {
                        "response": {
                            "correctResponse": "tone 3"
                        },
                        "display": {
                            "audioSrc": "sounds/toneresource/1.0mo/T3_400ms__vowel.wav"
                        }
                    }
                ]
            },
            {
                "stims": [
                    {
                        "response": {
                            "correctResponse": "tone 3"
                        },
                        "display": {
                            "audioSrc": "sounds/toneresource/1.0mo/T3_400ms__vowel_changeGender.wav"
                        }
                    }
                ]
            },
            {
                "stims": [
                    {
                        "response": {
                            "correctResponse": "tone 3"
                        },
                        "display": {
                            "audioSrc": "sounds/toneresource/1.8mo/T3_400ms__vowel.wav"
                        }
                    }
                ]
            },
            {
                "stims": [
                    {
                        "response": {
                            "correctResponse": "tone 3"
                        },
                        "display": {
                            "audioSrc": "sounds/toneresource/1.8mo/T3_400ms__vowel_changeGender.wav"
                        }
                    }
                ]
            },
            {
                "stims": [
                    {
                        "response": {
                            "correctResponse": "tone 3"
                        },
                        "display": {
                            "audioSrc": "sounds/toneresource/1.4mo/T3_800ms__vowel.wav"
                        }
                    }
                ]
            },
            {
                "stims": [
                    {
                        "response": {
                            "correctResponse": "tone 3"
                        },
                        "display": {
                            "audioSrc": "sounds/toneresource/1.4mo/T3_800ms__vowel_changeGender.wav"
                        }
                    }
                ]
            },
            {
                "stims": [
                    {
                        "response": {
                            "correctResponse": "tone 3"
                        },
                        "display": {
                            "audioSrc": "sounds/toneresource/1.0mo/T3_800ms__vowel.wav"
                        }
                    }
                ]
            },
            {
                "stims": [
                    {
                        "response": {
                            "correctResponse": "tone 3"
                        },
                        "display": {
                            "audioSrc": "sounds/toneresource/1.0mo/T3_800ms__vowel_changeGender.wav"
                        }
                    }
                ]
            },
            {
                "stims": [
                    {
                        "response": {
                            "correctResponse": "tone 3"
                        },
                        "display": {
                            "audioSrc": "sounds/toneresource/1.8mo/T3_800ms__vowel.wav"
                        }
                    }
                ]
            },
            {
                "stims": [
                    {
                        "response": {
                            "correctResponse": "tone 3"
                        },
                        "display": {
                            "audioSrc": "sounds/toneresource/1.8mo/T3_800ms__vowel_changeGender.wav"
                        }
                    }
                ]
            },
            {
                "stims": [
                    {
                        "response": {
                            "correctResponse": "tone 3"
                        },
                        "display": {
                            "audioSrc": "sounds/toneresource/1.4mo/T3_1200ms__vowel.wav"
                        }
                    }
                ]
            },
            {
                "stims": [
                    {
                        "response": {
                            "correctResponse": "tone 3"
                        },
                        "display": {
                            "audioSrc": "sounds/toneresource/1.4mo/T3_1200ms__vowel_changeGender.wav"
                        }
                    }
                ]
            },
            {
                "stims": [
                    {
                        "response": {
                            "correctResponse": "tone 3"
                        },
                        "display": {
                            "audioSrc": "sounds/toneresource/1.0mo/T3_1200ms__vowel.wav"
                        }
                    }
                ]
            },
            {
                "stims": [
                    {
                        "response": {
                            "correctResponse": "tone 3"
                        },
                        "display": {
                            "audioSrc": "sounds/toneresource/1.0mo/T3_1200ms__vowel_changeGender.wav"
                        }
                    }
                ]
            },
            {
                "stims": [
                    {
                        "response": {
                            "correctResponse": "tone 3"
                        },
                        "display": {
                            "audioSrc": "sounds/toneresource/1.8mo/T3_1200ms__vowel.wav"
                        }
                    }
                ]
            },
            {
                "stims": [
                    {
                        "response": {
                            "correctResponse": "tone 3"
                        },
                        "display": {
                            "audioSrc": "sounds/toneresource/1.8mo/T3_1200ms__vowel_changeGender.wav"
                        }
                    }
                ]
            },
            {
                "stims": [
                    {
                        "response": {
                            "correctResponse": "tone 4"
                        },
                        "display": {
                            "audioSrc": "sounds/toneresource/1.4ma/T4_400ms__vowel.wav"
                        }
                    }
                ]
            },
            {
                "stims": [
                    {
                        "response": {
                            "correctResponse": "tone 4"
                        },
                        "display": {
                            "audioSrc": "sounds/toneresource/1.4ma/T4_400ms__vowel_changeGender.wav"
                        }
                    }
                ]
            },
            {
                "stims": [
                    {
                        "response": {
                            "correctResponse": "tone 4"
                        },
                        "display": {
                            "audioSrc": "sounds/toneresource/1.0ma/T4_400ms__vowel.wav"
                        }
                    }
                ]
            },
            {
                "stims": [
                    {
                        "response": {
                            "correctResponse": "tone 4"
                        },
                        "display": {
                            "audioSrc": "sounds/toneresource/1.0ma/T4_400ms__vowel_changeGender.wav"
                        }
                    }
                ]
            },
            {
                "stims": [
                    {
                        "response": {
                            "correctResponse": "tone 4"
                        },
                        "display": {
                            "audioSrc": "sounds/toneresource/1.8ma/T4_400ms__vowel.wav"
                        }
                    }
                ]
            },
            {
                "stims": [
                    {
                        "response": {
                            "correctResponse": "tone 4"
                        },
                        "display": {
                            "audioSrc": "sounds/toneresource/1.8ma/T4_400ms__vowel_changeGender.wav"
                        }
                    }
                ]
            },
            {
                "stims": [
                    {
                        "response": {
                            "correctResponse": "tone 4"
                        },
                        "display": {
                            "audioSrc": "sounds/toneresource/1.4ma/T4_800ms__vowel.wav"
                        }
                    }
                ]
            },
            {
                "stims": [
                    {
                        "response": {
                            "correctResponse": "tone 4"
                        },
                        "display": {
                            "audioSrc": "sounds/toneresource/1.4ma/T4_800ms__vowel_changeGender.wav"
                        }
                    }
                ]
            },
            {
                "stims": [
                    {
                        "response": {
                            "correctResponse": "tone 4"
                        },
                        "display": {
                            "audioSrc": "sounds/toneresource/1.0ma/T4_800ms__vowel.wav"
                        }
                    }
                ]
            },
            {
                "stims": [
                    {
                        "response": {
                            "correctResponse": "tone 4"
                        },
                        "display": {
                            "audioSrc": "sounds/toneresource/1.0ma/T4_800ms__vowel_changeGender.wav"
                        }
                    }
                ]
            },
            {
                "stims": [
                    {
                        "response": {
                            "correctResponse": "tone 4"
                        },
                        "display": {
                            "audioSrc": "sounds/toneresource/1.8ma/T4_800ms__vowel.wav"
                        }
                    }
                ]
            },
            {
                "stims": [
                    {
                        "response": {
                            "correctResponse": "tone 4"
                        },
                        "display": {
                            "audioSrc": "sounds/toneresource/1.8ma/T4_800ms__vowel_changeGender.wav"
                        }
                    }
                ]
            },
            {
                "stims": [
                    {
                        "response": {
                            "correctResponse": "tone 4"
                        },
                        "display": {
                            "audioSrc": "sounds/toneresource/1.4ma/T4_1200ms__vowel.wav"
                        }
                    }
                ]
            },
            {
                "stims": [
                    {
                        "response": {
                            "correctResponse": "tone 4"
                        },
                        "display": {
                            "audioSrc": "sounds/toneresource/1.4ma/T4_1200ms__vowel_changeGender.wav"
                        }
                    }
                ]
            },
            {
                "stims": [
                    {
                        "response": {
                            "correctResponse": "tone 4"
                        },
                        "display": {
                            "audioSrc": "sounds/toneresource/1.0ma/T4_1200ms__vowel.wav"
                        }
                    }
                ]
            },
            {
                "stims": [
                    {
                        "response": {
                            "correctResponse": "tone 4"
                        },
                        "display": {
                            "audioSrc": "sounds/toneresource/1.0ma/T4_1200ms__vowel_changeGender.wav"
                        }
                    }
                ]
            },
            {
                "stims": [
                    {
                        "response": {
                            "correctResponse": "tone 4"
                        },
                        "display": {
                            "audioSrc": "sounds/toneresource/1.8ma/T4_1200ms__vowel.wav"
                        }
                    }
                ]
            },
            {
                "stims": [
                    {
                        "response": {
                            "correctResponse": "tone 4"
                        },
                        "display": {
                            "audioSrc": "sounds/toneresource/1.8ma/T4_1200ms__vowel_changeGender.wav"
                        }
                    }
                ]
            },
            {
                "stims": [
                    {
                        "response": {
                            "correctResponse": "tone 4"
                        },
                        "display": {
                            "audioSrc": "sounds/toneresource/1.4ya/T4_400ms__vowel.wav"
                        }
                    }
                ]
            },
            {
                "stims": [
                    {
                        "response": {
                            "correctResponse": "tone 4"
                        },
                        "display": {
                            "audioSrc": "sounds/toneresource/1.4ya/T4_400ms__vowel_changeGender.wav"
                        }
                    }
                ]
            },
            {
                "stims": [
                    {
                        "response": {
                            "correctResponse": "tone 4"
                        },
                        "display": {
                            "audioSrc": "sounds/toneresource/1.0ya/T4_400ms__vowel.wav"
                        }
                    }
                ]
            },
            {
                "stims": [
                    {
                        "response": {
                            "correctResponse": "tone 4"
                        },
                        "display": {
                            "audioSrc": "sounds/toneresource/1.0ya/T4_400ms__vowel_changeGender.wav"
                        }
                    }
                ]
            },
            {
                "stims": [
                    {
                        "response": {
                            "correctResponse": "tone 4"
                        },
                        "display": {
                            "audioSrc": "sounds/toneresource/1.8ya/T4_400ms__vowel.wav"
                        }
                    }
                ]
            },
            {
                "stims": [
                    {
                        "response": {
                            "correctResponse": "tone 4"
                        },
                        "display": {
                            "audioSrc": "sounds/toneresource/1.8ya/T4_400ms__vowel_changeGender.wav"
                        }
                    }
                ]
            },
            {
                "stims": [
                    {
                        "response": {
                            "correctResponse": "tone 4"
                        },
                        "display": {
                            "audioSrc": "sounds/toneresource/1.4ya/T4_800ms__vowel.wav"
                        }
                    }
                ]
            },
            {
                "stims": [
                    {
                        "response": {
                            "correctResponse": "tone 4"
                        },
                        "display": {
                            "audioSrc": "sounds/toneresource/1.4ya/T4_800ms__vowel_changeGender.wav"
                        }
                    }
                ]
            },
            {
                "stims": [
                    {
                        "response": {
                            "correctResponse": "tone 4"
                        },
                        "display": {
                            "audioSrc": "sounds/toneresource/1.0ya/T4_800ms__vowel.wav"
                        }
                    }
                ]
            },
            {
                "stims": [
                    {
                        "response": {
                            "correctResponse": "tone 4"
                        },
                        "display": {
                            "audioSrc": "sounds/toneresource/1.0ya/T4_800ms__vowel_changeGender.wav"
                        }
                    }
                ]
            },
            {
                "stims": [
                    {
                        "response": {
                            "correctResponse": "tone 4"
                        },
                        "display": {
                            "audioSrc": "sounds/toneresource/1.8ya/T4_800ms__vowel.wav"
                        }
                    }
                ]
            },
            {
                "stims": [
                    {
                        "response": {
                            "correctResponse": "tone 4"
                        },
                        "display": {
                            "audioSrc": "sounds/toneresource/1.8ya/T4_800ms__vowel_changeGender.wav"
                        }
                    }
                ]
            },
            {
                "stims": [
                    {
                        "response": {
                            "correctResponse": "tone 4"
                        },
                        "display": {
                            "audioSrc": "sounds/toneresource/1.4ya/T4_1200ms__vowel.wav"
                        }
                    }
                ]
            },
            {
                "stims": [
                    {
                        "response": {
                            "correctResponse": "tone 4"
                        },
                        "display": {
                            "audioSrc": "sounds/toneresource/1.4ya/T4_1200ms__vowel_changeGender.wav"
                        }
                    }
                ]
            },
            {
                "stims": [
                    {
                        "response": {
                            "correctResponse": "tone 4"
                        },
                        "display": {
                            "audioSrc": "sounds/toneresource/1.0ya/T4_1200ms__vowel.wav"
                        }
                    }
                ]
            },
            {
                "stims": [
                    {
                        "response": {
                            "correctResponse": "tone 4"
                        },
                        "display": {
                            "audioSrc": "sounds/toneresource/1.0ya/T4_1200ms__vowel_changeGender.wav"
                        }
                    }
                ]
            },
            {
                "stims": [
                    {
                        "response": {
                            "correctResponse": "tone 4"
                        },
                        "display": {
                            "audioSrc": "sounds/toneresource/1.8ya/T4_1200ms__vowel.wav"
                        }
                    }
                ]
            },
            {
                "stims": [
                    {
                        "response": {
                            "correctResponse": "tone 4"
                        },
                        "display": {
                            "audioSrc": "sounds/toneresource/1.8ya/T4_1200ms__vowel_changeGender.wav"
                        }
                    }
                ]
            },
            {
                "stims": [
                    {
                        "response": {
                            "correctResponse": "tone 4"
                        },
                        "display": {
                            "audioSrc": "sounds/toneresource/1.4mo/T4_400ms__vowel.wav"
                        }
                    }
                ]
            },
            {
                "stims": [
                    {
                        "response": {
                            "correctResponse": "tone 4"
                        },
                        "display": {
                            "audioSrc": "sounds/toneresource/1.4mo/T4_400ms__vowel_changeGender.wav"
                        }
                    }
                ]
            },
            {
                "stims": [
                    {
                        "response": {
                            "correctResponse": "tone 4"
                        },
                        "display": {
                            "audioSrc": "sounds/toneresource/1.0mo/T4_400ms__vowel.wav"
                        }
                    }
                ]
            },
            {
                "stims": [
                    {
                        "response": {
                            "correctResponse": "tone 4"
                        },
                        "display": {
                            "audioSrc": "sounds/toneresource/1.0mo/T4_400ms__vowel_changeGender.wav"
                        }
                    }
                ]
            },
            {
                "stims": [
                    {
                        "response": {
                            "correctResponse": "tone 4"
                        },
                        "display": {
                            "audioSrc": "sounds/toneresource/1.8mo/T4_400ms__vowel.wav"
                        }
                    }
                ]
            },
            {
                "stims": [
                    {
                        "response": {
                            "correctResponse": "tone 4"
                        },
                        "display": {
                            "audioSrc": "sounds/toneresource/1.8mo/T4_400ms__vowel_changeGender.wav"
                        }
                    }
                ]
            },
            {
                "stims": [
                    {
                        "response": {
                            "correctResponse": "tone 4"
                        },
                        "display": {
                            "audioSrc": "sounds/toneresource/1.4mo/T4_800ms__vowel.wav"
                        }
                    }
                ]
            },
            {
                "stims": [
                    {
                        "response": {
                            "correctResponse": "tone 4"
                        },
                        "display": {
                            "audioSrc": "sounds/toneresource/1.4mo/T4_800ms__vowel_changeGender.wav"
                        }
                    }
                ]
            },
            {
                "stims": [
                    {
                        "response": {
                            "correctResponse": "tone 4"
                        },
                        "display": {
                            "audioSrc": "sounds/toneresource/1.0mo/T4_800ms__vowel.wav"
                        }
                    }
                ]
            },
            {
                "stims": [
                    {
                        "response": {
                            "correctResponse": "tone 4"
                        },
                        "display": {
                            "audioSrc": "sounds/toneresource/1.0mo/T4_800ms__vowel_changeGender.wav"
                        }
                    }
                ]
            },
            {
                "stims": [
                    {
                        "response": {
                            "correctResponse": "tone 4"
                        },
                        "display": {
                            "audioSrc": "sounds/toneresource/1.8mo/T4_800ms__vowel.wav"
                        }
                    }
                ]
            },
            {
                "stims": [
                    {
                        "response": {
                            "correctResponse": "tone 4"
                        },
                        "display": {
                            "audioSrc": "sounds/toneresource/1.8mo/T4_800ms__vowel_changeGender.wav"
                        }
                    }
                ]
            },
            {
                "stims": [
                    {
                        "response": {
                            "correctResponse": "tone 4"
                        },
                        "display": {
                            "audioSrc": "sounds/toneresource/1.4mo/T4_1200ms__vowel.wav"
                        }
                    }
                ]
            },
            {
                "stims": [
                    {
                        "response": {
                            "correctResponse": "tone 4"
                        },
                        "display": {
                            "audioSrc": "sounds/toneresource/1.4mo/T4_1200ms__vowel_changeGender.wav"
                        }
                    }
                ]
            },
            {
                "stims": [
                    {
                        "response": {
                            "correctResponse": "tone 4"
                        },
                        "display": {
                            "audioSrc": "sounds/toneresource/1.0mo/T4_1200ms__vowel.wav"
                        }
                    }
                ]
            },
            {
                "stims": [
                    {
                        "response": {
                            "correctResponse": "tone 4"
                        },
                        "display": {
                            "audioSrc": "sounds/toneresource/1.0mo/T4_1200ms__vowel_changeGender.wav"
                        }
                    }
                ]
            },
            {
                "stims": [
                    {
                        "response": {
                            "correctResponse": "tone 4"
                        },
                        "display": {
                            "audioSrc": "sounds/toneresource/1.8mo/T4_1200ms__vowel.wav"
                        }
                    }
                ]
            },
            {
                "stims": [
                    {
                        "response": {
                            "correctResponse": "tone 4"
                        },
                        "display": {
                            "audioSrc": "sounds/toneresource/1.8mo/T4_1200ms__vowel_changeGender.wav"
                        }
                    }
                ]
            },
            {
                "stims": [
                    {
                        "response": {
                            "correctResponse": "0",
                            "incorrectResponses": [
                                "1-4",
                                "5-10",
                                "10-20",
                                "20 and over"
                            ]
                        },
                        "display": {
                            "text": "How many missing sounds or delayed sounds did you hear in the experiment?"
                        }
                    }
                ]
            },
            {
                "stims": [
                    {
                        "response": {
                            "correctResponse": "alpha"
                        },
                        "display": {
                            "text": "Did you have any technical problems? After you input the answer, click the Enter button to go on."
                        }
                    }
                ]
            },
            {
                "stims": [
                    {
                        "response": {
                            "correctResponse": "Yes",
                            "incorrectResponses": [
                                "No"
                            ]
                        },
                        "display": {
                            "text": "Did you wear your headphone when you did the experiment?"
                        }
                    }
                ]
            },
            {
                "stims": [
                    {
                        "response": {
                            "correctResponse": "18-25",
                            "incorrectResponses": [
                                "26-34",
                                "35-54",
                                "55-64",
                                "65 and over"
                            ]
                        },
                        "display": {
                            "text": "Age?"
                        }
                    }
                ]
            },
            {
                "stims": [
                    {
                        "response": {
                            "correctResponse": "Male",
                            "incorrectResponses": [
                                "Female",
                                "Other",
                                "Prefer not to answer"
                            ]
                        },
                        "display": {
                            "text": "Gender?"
                        }
                    }
                ]
            },
            {
                "stims": [
                    {
                        "response": {
                            "correctResponse": "Less than High School",
                            "incorrectResponses": [
                                "High School or GED",
                                "Some College",
                                "4-year College Degree/ Bachelors",
                                "Graduate Degree"
                            ]
                        },
                        "display": {
                            "text": "Which is the highest level of education you have completed?"
                        }
                    }
                ]
            },
            {
                "stims": [
                    {
                        "response": {
                            "correctResponse": "alpha"
                        },
                        "display": {
                            "text": "What's your native language? After you input the answer, click the Enter button to go on."
                        }
                    }
                ]
            },
            {
                "stims": [
                    {
                        "response": {
                            "correctResponse": "0",
                            "incorrectResponses": [
                                "1",
                                "2-5",
                                "5 and more"
                            ]
                        },
                        "display": {
                            "text": "How many years have you received the musical training?"
                        }
                    }
                ]
            },
            {
                "stims": [
                    {
                        "response": {
                            "correctResponse": "0",
                            "incorrectResponses": [
                                "1",
                                "2-5",
                                "5 and more",
                                "My native language is a kind of tonal language."
                            ]
                        },
                        "display": {
                            "text": "How many years have you studied tonal language?"
                        }
                    }
                ]
            }
        ]
    }
}