{
  "format": "isopack-2-unibuild",
  "declaredExports": [
    {
      "name": "Tracker",
      "testOnly": false
    },
    {
      "name": "Deps",
      "testOnly": false
    }
  ],
  "uses": [
    {
      "package": "meteor"
    },
    {
      "package": "ecmascript"
    }
  ],
  "resources": [
    {
      "type": "source",
      "extension": "js",
      "file": "os/tracker.js",
      "length": 19776,
      "offset": 0,
      "path": "tracker.js",
      "hash": "ccb94d7b780aea9de93b4e78aa8654de7cd45c7c",
      "fileOptions": {
        "lazy": false
      }
    },
    {
      "type": "source",
      "extension": "js",
      "file": "os/tracker_tests.js",
      "length": 12335,
      "offset": 0,
      "path": "tracker_tests.js",
      "hash": "f6560b4228dc8f8e89b287baccc63c2b66684de6",
      "fileOptions": {
        "lazy": true
      }
    }
  ]
}