{
  "format": "isopack-2-unibuild",
  "declaredExports": [
    {
      "name": "MeteorDeveloperAccounts",
      "testOnly": false
    }
  ],
  "uses": [
    {
      "package": "meteor"
    },
    {
      "package": "oauth2",
      "constraint": "1.3.1"
    },
    {
      "package": "oauth",
      "constraint": "2.0.0"
    },
    {
      "package": "ecmascript",
      "constraint": "0.15.2"
    },
    {
      "package": "service-configuration",
      "constraint": "1.1.0"
    },
    {
      "package": "random",
      "constraint": "1.2.0"
    }
  ],
  "resources": [
    {
      "type": "source",
      "extension": "js",
      "file": "web.browser.legacy/meteor_developer_common.js",
      "length": 342,
      "offset": 0,
      "path": "meteor_developer_common.js",
      "hash": "eda6e97c3504ae63d9290cccf424cdc05905374d",
      "fileOptions": {
        "lazy": false
      }
    },
    {
      "type": "source",
      "extension": "js",
      "file": "web.browser.legacy/meteor_developer_client.js",
      "length": 1862,
      "offset": 0,
      "path": "meteor_developer_client.js",
      "hash": "a8aa46109473db6d129cb5188f7f0886aed2428d",
      "fileOptions": {
        "lazy": false
      }
    },
    {
      "type": "source",
      "extension": "js",
      "file": "web.browser.legacy/meteor_developer_server.js",
      "length": 2835,
      "offset": 0,
      "path": "meteor_developer_server.js",
      "hash": "8afd4179beee4cc876bf4f6c3433004176490865",
      "fileOptions": {
        "lazy": true
      }
    }
  ]
}